dcalendario/__init__.py
dcalendario/dcalendario.py
dcalendario-0.2.3.dist-info/LICENSE
dcalendario-0.2.3.dist-info/METADATA
dcalendario-0.2.3.dist-info/WHEEL
dcalendario-0.2.3.dist-info/top_level.txt
dcalendario-0.2.3.dist-info/RECORD
