Metadata-Version: 2.1
Name: dcalendario
Version: 0.2.3
Summary: Pacote para gerar uma tabela dCalendário com Python
Home-page: https://github.com/CarlosEX/dCalendario
Author: Carlos Antonio
Author-email: carlos22martinssilva@gmail.com
License: UNKNOWN
Platform: UNKNOWN
Classifier: Programming Language :: Python :: 3
Classifier: License :: OSI Approved :: MIT License
Classifier: Operating System :: OS Independent
Requires-Python: >=3.6
License-File: LICENSE
Requires-Dist: pandas
Requires-Dist: numpy
Requires-Dist: babel
